{
    "players": [
      {
        "id": "1",
         "name": "Αργύρης Αλευράς",
        "position": "GK",
        "image": "images/1.png"
      },
      
      {
        "id":"5",
         "name": "Αποστόλης Οικονομόπουλος",
        "position": "CB",
        "image": "images/5.png"
     },
      {
        
         "id":"4",
         "name": "Παναγιώτης Σκαλτσάς",
        "position": "CB",
        "image": "images/4.png"
     },
     {
        "id":"3",
         "name": "Αλκιβιάδης Καζάς",
        "position": "LB/RB",
        "image": ""
     },
     {
        "id":"6",
         "name": "Χριστόφορος Κουτσοποδιώτης",
        "position": "RB/CM",
        "image": ""
     },
     {
        "id":"7",
         "name": "Agustin Tresa",
        "position": "CDM/CAM",
        "image": "images/7.png"
     },
     {
        "id":"10",
         "name": "Χρήστο Κέλλι",
        "position": "ST/RW/LW/CAM",
        "image": "images/10.png"
     },
     {
      "id":"11",  
      "name": "Ανάργυρος Αποστόλου",
        "position": "RW",
        "image": "images/11.png"
     },
     {
        "id":"8",
         "name": "Ανάργυρος Λαζάρου",
        "position": "CB/CDM",
        "image": "images/8.png"
     },
     {
      "id":"9",  
      "name": "Νικόλας Λαζάρου",
        "position": "ST",
        "image": "images/9.png"
     },
     {
      "id":"13",  
      "name": "Γιώργος Μπάρδης",
        "position": "LB",
        "image": "images/13.png"
     },
     {
      "id":"2",  
      "name": "Φάνης Παπασταύρου",
        "position": "RB/CM",
        "image": "images/2.png"
     },
     {
      "id":"12",  
      "name": "Γιάννης Μπάρδης",
        "position": "CAM",
        "image": "images/12.png"
     },
     {
      "id":"14",  
      "name": "Γιώργος Αντουλινάκης",
        "position": "ST",
        "image": "images/14.png"
     },
     {
      "id":"15",  
      "name": "Εφραίμ Κοτζαμάνης",
        "position": "ST/RW/LW/CAM",
        "image": "images/16.png"
     },
     {
      "id":"16",  
      "name": "Μαρικλέν Τοπάλλι",
        "position": "LB",
        "image": ""
     },
     {
      "id":"17",  
      "name": "Νου Γκιονάι",
        "position": "RW",
        "image": "images/18.png"
     },
     {
      "id":"18",  
      "name": "Νικόλας Χασκάι",
        "position": "RW",
        "image": "images/17.png"
     },
     {
      "id":"19",  
      "name": "Πέτρος Πρένγκα",
        "position": "RB",
        "image": "images/19.png"
     },
     {
      "id":"20",  
      "name": "Βαγγέλης Προσίλης",
        "position": "LB/LW/CM",
        "image": "images/20.png"
     }
     

    ]
  }