{
    "moments": [
        {
            "url": "https://scontent.fath4-2.fna.fbcdn.net/v/t39.30808-6/463479413_589335530138350_8760454376248246463_n.jpg?_nc_cat=102&ccb=1-7&_nc_sid=127cfc&_nc_ohc=CcY_FBeoItUQ7kNvgFuKpYA&_nc_zt=23&_nc_ht=scontent.fath4-2.fna&_nc_gid=AyHQ0qdehNdp_hKL-Lmbmzk&oh=00_AYCCjkLq43WZJT66Q5AI5rW9GMMgmcGNdhdc6-kN_ie1lw&oe=672D5D02",
            "caption": "Πανηγυρισμοί μετά το πρώτο γκολ του Χριστόφορου Κουτσοποδιώτη (2-2 Ποσειδών - Πανασιναϊκός 20/10/2024)"
        },
        {
            "url": "https://scontent.fath4-2.fna.fbcdn.net/v/t39.30808-6/422023345_427121053026466_8882252286454753730_n.jpg?_nc_cat=106&ccb=1-7&_nc_sid=127cfc&_nc_ohc=HrwGsJkz70EQ7kNvgF2G39d&_nc_zt=23&_nc_ht=scontent.fath4-2.fna&_nc_gid=AL3qdLvaSZ9bPyl1QOuDBdd&oh=00_AYBt00GoPoV3CbcaxNCLmmvNlUF9s8Kw0LKAuceLhOeU8w&oe=672D8362",
            "caption": "Στιγμές πριν το γκολ του Νίκου Λαζάρου για το 0-1 στην Κοιλάδα (2-1 Κορωνίς - Ποσειδών 4/2/2024)"
        },
        {
            "url": "https://scontent.fath4-2.fna.fbcdn.net/v/t39.30808-6/410940463_397964515942120_1857583871465580898_n.jpg?_nc_cat=109&ccb=1-7&_nc_sid=f727a1&_nc_ohc=lwbvKzCtlnUQ7kNvgG3BSmg&_nc_zt=23&_nc_ht=scontent.fath4-2.fna&_nc_gid=ATgolpa4dK7iPujnNXw4ThI&oh=00_AYBxt_eI-gaGrQaoS6-t5_QiKtWS2-zdApvjqoxV8Hb_UA&oe=672D7906",
            "caption": "Αγώνας ενάντια στον Τροιζηνιακό (0-0 Τροιζηνιακός - Ποσειδών 18/12/2023)"
        },
        {
            "url" : "https://scontent.fath4-2.fna.fbcdn.net/v/t39.30808-6/317975763_213046287767278_2355926238697112629_n.jpg?_nc_cat=104&ccb=1-7&_nc_sid=127cfc&_nc_ohc=Agc-KbdPxTYQ7kNvgHHHBG7&_nc_zt=23&_nc_ht=scontent.fath4-2.fna&_nc_gid=A48jYTDIrYoGJRHwioUElfZ&oh=00_AYCDl8LJ2EQkBjfxn-sdZnBPvoDE71mZZkNgpbXki1ufKA&oe=672D71C7",
            "caption":"Στιγμές μετά το τραυματισμό του Ανάργυρου Λαζάρου (2-1 Ηρακλής Καρυάς - Ποσειδών 4/12/2022)"
        },
        {
            "url": "https://scontent.fath4-2.fna.fbcdn.net/v/t39.30808-6/315548771_209616141443626_6493759344173297696_n.jpg?_nc_cat=111&ccb=1-7&_nc_sid=127cfc&_nc_ohc=8EKUjpCNrJAQ7kNvgGBtzxD&_nc_zt=23&_nc_ht=scontent.fath4-2.fna&_nc_gid=A__F_0i3a_oFgDFsk_T1ZoX&oh=00_AYB-jAa0jLda2liduYPZpdr27ZcD3d-7NnS4FGCMVu3AIg&oe=672D729A",
            "caption": "Βαγγέλης και Αγκουστίν Τρέσα, σε έναν αγώνα κυπέλλου (1-4 Ποσειδών - Ένωση Ερμιονίδας 16/11/2022)"
        },
        {
            "url": "https://scontent.fath4-2.fna.fbcdn.net/v/t39.30808-6/430062390_447772734294631_6436774489432932098_n.jpg?_nc_cat=102&ccb=1-7&_nc_sid=127cfc&_nc_ohc=fnpbw1Kq_hEQ7kNvgHRgF8h&_nc_zt=23&_nc_ht=scontent.fath4-2.fna&_nc_gid=Avz7uQSqAIY4SQLqpisJ0xu&oh=00_AYDOkaFMfkttti682bz6aQExJJERlv_aQhUzdVzlqWeBLg&oe=672D8AD4",
            "caption": "4-0 Ποσειδών - Πανασιναϊκός 10/3/2024"
        }
    ]
}